ni/panels/v1/__init__.py
ni/panels/v1/panel_service_pb2.py
ni/panels/v1/panel_service_pb2.pyi
ni/panels/v1/panel_service_pb2_grpc.py
ni/panels/v1/panel_service_pb2_grpc.pyi
ni/panels/v1/py.typed
ni/panels/v1/streamlit_panel_configuration_pb2.py
ni/panels/v1/streamlit_panel_configuration_pb2.pyi
ni_panels_v1_proto-1.0.0.dist-info/METADATA
ni_panels_v1_proto-1.0.0.dist-info/WHEEL
ni_panels_v1_proto-1.0.0.dist-info/RECORD
