Metadata-Version: 2.3
Name: ni.panels.v1.proto
Version: 1.0.0
Summary: Protobuf generated code for the ni.panels.v1 gRPC API
License: MIT
Keywords: ni-apis,protobuf,panels
Author: NI
Author-email: opensource@ni.com
Maintainer: Joe Friedrichsen
Maintainer-email: joe.friedrichsen@emerson.com
Requires-Python: >=3.10,<4.0
Classifier: Development Status :: 5 - Production/Stable
Classifier: Intended Audience :: Developers
Classifier: Intended Audience :: Manufacturing
Classifier: Intended Audience :: Science/Research
Classifier: License :: OSI Approved :: MIT License
Classifier: Operating System :: Microsoft :: Windows
Classifier: Operating System :: POSIX
Classifier: Programming Language :: Python :: 3
Classifier: Programming Language :: Python :: 3.10
Classifier: Programming Language :: Python :: 3.11
Classifier: Programming Language :: Python :: 3.12
Classifier: Programming Language :: Python :: 3.13
Classifier: Programming Language :: Python :: 3.14
Classifier: Programming Language :: Python :: Implementation :: CPython
Requires-Dist: grpcio (>=1.49.0,<2.0)
Requires-Dist: protobuf (>=4.21)
Project-URL: Documentation, https://nipanelsv1proto.readthedocs.io/en/latest/
Project-URL: Repository, https://github.com/ni/ni-apis-python
